sphinxext/remoteliteralinclude.py
sphinxext_remoteliteralinclude-0.6.0.dist-info/LICENSE.md
sphinxext_remoteliteralinclude-0.6.0.dist-info/METADATA
sphinxext_remoteliteralinclude-0.6.0.dist-info/WHEEL
sphinxext_remoteliteralinclude-0.6.0.dist-info/top_level.txt
sphinxext_remoteliteralinclude-0.6.0.dist-info/RECORD
